{
  "title": {
    "en": "Adjectives of Abstract Human Attributes",
    "id": "Kata sifat atribut manusia abstrak"
  },
  "description": {
    "en": "These classes of adjectives describe abstract attributes of humans such as their intellectual, personal, interpersonal, and moral attributes.",
    "id": "Kelas kata sifat ini menggambarkan atribut abstrak manusia seperti atribut intelektual, pribadi, interpersonal, dan moral mereka."
  },
  "list": [
    {
      "id": "4260",
      "adverbTitle": "Adjectives of Positive Intellectual Traits",
      "words": "35",
      "time": "18"
    },
    {
      "id": "4261",
      "adverbTitle": "Adjectives of Skill and Aptitude",
      "words": "20",
      "time": "11"
    },
    {
      "id": "4262",
      "adverbTitle": "Adjectives of Negative Intellectual Traits",
      "words": "28",
      "time": "15"
    },
    {
      "id": "4265",
      "adverbTitle": "Adjectives of Positive Personal Traits",
      "words": "35",
      "time": "18"
    },
    {
      "id": "4266",
      "adverbTitle": "Adjectives of Positive Interpersonal Traits",
      "words": "42",
      "time": "22"
    },
    {
      "id": "4267",
      "adverbTitle": "Adjectives of Negative Personal Traits",
      "words": "29",
      "time": "15"
    },
    {
      "id": "4268",
      "adverbTitle": "Adjectives of Negative Interpersonal Traits",
      "words": "33",
      "time": "17"
    },
    {
      "id": "4269",
      "adverbTitle": "Adjectives of Neutral Personal Traits",
      "words": "22",
      "time": "12"
    },
    {
      "id": "4270",
      "adverbTitle": "Adjectives of Neutral Interpersonal Traits",
      "words": "16",
      "time": "9"
    },
    {
      "id": "4271",
      "adverbTitle": "Adjectives of Positive Moral Traits",
      "words": "24",
      "time": "13"
    },
    {
      "id": "4272",
      "adverbTitle": "Adjectives of Negative Moral Traits",
      "words": "31",
      "time": "16"
    },
    {
      "id": "4273",
      "adverbTitle": "Adjectives of Positive Temporary Mental States",
      "words": "28",
      "time": "15"
    },
    {
      "id": "4274",
      "adverbTitle": "Adjectives of Negative Temporary Mental States",
      "words": "26",
      "time": "14"
    },
    {
      "id": "4275",
      "adverbTitle": "Adjectives of Neutral Temporary Mental States",
      "words": "18",
      "time": "10"
    }
  ],
  "id": 179
}