{
  "id": 3127,
  "title": {
    "en": "Unit 2 - 2D",
    "id": "Unit 2 - 2D"
  },
  "description": {
    "en": "Here you will find the vocabulary from Unit 2 - 2D in the Insight Elementary coursebook, such as \"Portuguese\", \"language\", \"Dutch\", etc.",
    "id": "Di sini Anda akan menemukan kosa kata dari Unit 2 - 2D di buku kursus Dasar Insight, seperti \"Portugis\", \"bahasa\", \"Belanda\", dll."
  },
  "cards": [
    {
      "id": 317933,
      "translation": {
        "en": {
          "short": "language",
          "long": "the system of communication by spoken or written words, that the people of a particular country or region use",
          "partOfSpeech": "noun"
        },
        "id": {
          "short": "bahasa",
          "long": "Sistem komunikasi dengan kata -kata lisan atau tertulis, yang digunakan oleh orang -orang dari negara atau wilayah tertentu",
          "partOfSpeech": "kata benda"
        }
      },
      "image": "https://dictionary.hanzi.id/images/317933.jpeg",
      "simplified": "语",
      "traditional": "語",
      "pinyin": "yǔ"
    },
    {
      "id": 317934,
      "translation": {
        "en": {
          "short": "Chinese",
          "long": "any of the Sino-Tibetan languages of China",
          "partOfSpeech": "noun"
        },
        "id": {
          "short": "Cina",
          "long": "salah satu bahasa Sino-Tibet di Tiongkok",
          "partOfSpeech": "kata benda"
        }
      },
      "image": "https://dictionary.hanzi.id/images/317934.jpeg",
      "simplified": "中文",
      "traditional": "中文",
      "pinyin": "Zhōngwén"
    },
    {
      "id": 317935,
      "translation": {
        "en": {
          "short": "Dutch",
          "long": "the main language in the Netherlands",
          "partOfSpeech": "noun"
        },
        "id": {
          "short": "Belanda",
          "long": "bahasa utama di Belanda",
          "partOfSpeech": "kata benda"
        }
      },
      "image": "https://dictionary.hanzi.id/images/317935.jpeg",
      "simplified": "荷兰语",
      "traditional": "荷蘭語",
      "pinyin": "Hélán yǔ"
    },
    {
      "id": 317937,
      "translation": {
        "en": {
          "short": "English",
          "long": "the most common language in the world, originating in England but also the official language of America, Canada, Australia, etc.",
          "partOfSpeech": "noun"
        },
        "id": {
          "short": "Bahasa inggris",
          "long": "Bahasa paling umum di dunia, yang berasal dari Inggris tetapi juga bahasa resmi Amerika, Kanada, Australia, dll.",
          "partOfSpeech": "kata benda"
        }
      },
      "image": "https://dictionary.hanzi.id/images/317937.jpeg",
      "simplified": "英语",
      "traditional": "英語",
      "pinyin": "Yīngyǔ"
    },
    {
      "id": 317938,
      "translation": {
        "en": {
          "short": "French",
          "long": "the main language of France that is also spoken in parts of other countries such as Canada, Switzerland, Belgium, etc.",
          "partOfSpeech": "noun"
        },
        "id": {
          "short": "Perancis",
          "long": "Bahasa utama Prancis yang juga diucapkan di beberapa negara lain seperti Kanada, Swiss, Belgia, dll.",
          "partOfSpeech": "kata benda"
        }
      },
      "image": "https://dictionary.hanzi.id/images/317938.jpeg",
      "simplified": "法语",
      "traditional": "法語",
      "pinyin": "Fǎyǔ"
    },
    {
      "id": 317939,
      "translation": {
        "en": {
          "short": "Hungarian",
          "long": "a language spoken mainly in Hungary and neighboring countries such as Romania and Ukraine",
          "partOfSpeech": "noun"
        },
        "id": {
          "short": "Hongaria",
          "long": "Bahasa yang diucapkan terutama di negara -negara Hongaria dan tetangga seperti Rumania dan Ukraina",
          "partOfSpeech": "kata benda"
        }
      },
      "image": "https://dictionary.hanzi.id/images/317939.jpeg",
      "simplified": "匈牙利",
      "traditional": "匈牙利",
      "pinyin": "Xiōngyá lì"
    },
    {
      "id": 317940,
      "translation": {
        "en": {
          "short": "Italian",
          "long": "the main language in Italy, and in parts of Switzerland",
          "partOfSpeech": "noun"
        },
        "id": {
          "short": "Italia",
          "long": "bahasa utama di Italia, dan di beberapa bagian Swiss",
          "partOfSpeech": "kata benda"
        }
      },
      "image": "https://dictionary.hanzi.id/images/317940.jpeg",
      "simplified": "意大利人",
      "traditional": "意大利人",
      "pinyin": "Yìdà lì rén"
    },
    {
      "id": 317941,
      "translation": {
        "en": {
          "short": "Japanese",
          "long": "the language spoken in Japan",
          "partOfSpeech": "noun"
        },
        "id": {
          "short": "Jepang",
          "long": "bahasa yang diucapkan di Jepang",
          "partOfSpeech": "kata benda"
        }
      },
      "image": "https://dictionary.hanzi.id/images/317941.jpeg",
      "simplified": "日语",
      "traditional": "日語",
      "pinyin": "Rìyǔ"
    },
    {
      "id": 317942,
      "translation": {
        "en": {
          "short": "Polish",
          "long": "Poland's official language",
          "partOfSpeech": "noun"
        },
        "id": {
          "short": "Polandia",
          "long": "Bahasa resmi Polandia",
          "partOfSpeech": "kata benda"
        }
      },
      "image": "https://dictionary.hanzi.id/images/317942.jpeg",
      "simplified": "波兰语",
      "traditional": "波蘭語",
      "pinyin": "Bōlán yǔ"
    },
    {
      "id": 317943,
      "translation": {
        "en": {
          "short": "Portuguese",
          "long": "the Romance language of Portugal and Brazil",
          "partOfSpeech": "noun"
        },
        "id": {
          "short": "Portugis",
          "long": "bahasa romansa Portugal dan Brasil",
          "partOfSpeech": "kata benda"
        }
      },
      "image": "https://dictionary.hanzi.id/images/317943.jpeg",
      "simplified": "葡萄牙语",
      "traditional": "葡萄牙語",
      "pinyin": "Pútáo yá yǔ"
    },
    {
      "id": 317944,
      "translation": {
        "en": {
          "short": "Russian",
          "long": "the official language of Russia",
          "partOfSpeech": "noun"
        },
        "id": {
          "short": "Rusia",
          "long": "bahasa resmi Rusia",
          "partOfSpeech": "kata benda"
        }
      },
      "image": "https://dictionary.hanzi.id/images/317944.jpeg",
      "simplified": "俄语",
      "traditional": "俄語",
      "pinyin": "E2yǔ"
    },
    {
      "id": 317945,
      "translation": {
        "en": {
          "short": "Spanish",
          "long": "the main language of Spain and many Southern or Central American countries",
          "partOfSpeech": "noun"
        },
        "id": {
          "short": "Orang Spanyol",
          "long": "Bahasa utama Spanyol dan banyak negara selatan atau Amerika Tengah",
          "partOfSpeech": "kata benda"
        }
      },
      "image": "https://dictionary.hanzi.id/images/317945.jpeg",
      "simplified": "西班牙语",
      "traditional": "西班牙語",
      "pinyin": "Xībān yá yǔ"
    }
  ]
}