{
  "id": 4863,
  "title": {
    "en": "Adverbs of Undesirable High Extent",
    "id": "Kata keterangan tingkat tinggi yang tidak diinginkan"
  },
  "description": {
    "en": "These adverbs are used to indicate that something bad and undesirable exists or happens to a large extent, such as \"terribly\", \"severely\", \"grossly\", etc.",
    "id": "Adverbia ini digunakan untuk menunjukkan bahwa sesuatu yang buruk dan tidak diinginkan ada atau terjadi sebagian besar, seperti \"sangat\", \"sangat\", \"sangat\", dll."
  },
  "cards": [
    {
      "id": 372251,
      "translation": {
        "en": {
          "short": "way",
          "long": "used to emphasize the amount or intensity of something",
          "partOfSpeech": "adverb"
        },
        "id": {
          "short": "jalan",
          "long": "digunakan untuk menekankan jumlah atau intensitas sesuatu",
          "partOfSpeech": "kata keterangan"
        }
      },
      "image": "https://dictionary.hanzi.id/images/372251.jpeg",
      "simplified": "非常",
      "traditional": "非常",
      "pinyin": "Fēicháng"
    },
    {
      "id": 372252,
      "translation": {
        "en": {
          "short": "far",
          "long": "to a large degree",
          "partOfSpeech": "adverb"
        },
        "id": {
          "short": "jauh",
          "long": "sebagian besar",
          "partOfSpeech": "kata keterangan"
        }
      },
      "image": null,
      "simplified": "远的",
      "traditional": "遠的",
      "pinyin": "yuǎn de"
    },
    {
      "id": 372253,
      "translation": {
        "en": {
          "short": "overwhelmingly",
          "long": "to a very great degree that cannot be resisted",
          "partOfSpeech": "adverb"
        },
        "id": {
          "short": "sangat",
          "long": "ke tingkat yang sangat besar yang tidak dapat ditolak",
          "partOfSpeech": "kata keterangan"
        }
      },
      "image": "https://dictionary.hanzi.id/images/372253.jpeg",
      "simplified": "以一种令人惊奇的方式",
      "traditional": "以一種令人驚奇的方式",
      "pinyin": "yǐ yīzhǒng lìng rén jīngqí de fāngshì"
    },
    {
      "id": 372254,
      "translation": {
        "en": {
          "short": "severely",
          "long": "very badly or to a serious extent",
          "partOfSpeech": "adverb"
        },
        "id": {
          "short": "sangat besar",
          "long": "sangat buruk atau pada tingkat yang serius",
          "partOfSpeech": "kata keterangan"
        }
      },
      "image": "https://dictionary.hanzi.id/images/372254.jpeg",
      "simplified": "严重",
      "traditional": "嚴重",
      "pinyin": "yánzhòng"
    },
    {
      "id": 372255,
      "translation": {
        "en": {
          "short": "drastically",
          "long": "to an extreme or great degree",
          "partOfSpeech": "adverb"
        },
        "id": {
          "short": "secara drastis",
          "long": "ke tingkat yang ekstrem atau luar biasa",
          "partOfSpeech": "kata keterangan"
        }
      },
      "image": "https://dictionary.hanzi.id/images/372255.jpeg",
      "simplified": "彻底地",
      "traditional": "徹底地",
      "pinyin": "chèdǐ dì"
    },
    {
      "id": 372257,
      "translation": {
        "en": {
          "short": "unbearably",
          "long": "in a manner that is very hard or impossible to tolerate",
          "partOfSpeech": "adverb"
        },
        "id": {
          "short": "tak tertahankan",
          "long": "dengan cara yang sangat sulit atau tidak mungkin untuk ditoleransi",
          "partOfSpeech": "kata keterangan"
        }
      },
      "image": "https://dictionary.hanzi.id/images/372257.jpeg",
      "simplified": "难以忍受地",
      "traditional": "難以忍受地",
      "pinyin": "nányǐ rěnshòu de"
    },
    {
      "id": 372258,
      "translation": {
        "en": {
          "short": "critically",
          "long": "to an extent or degree that is possibly catastrophic or disastrous",
          "partOfSpeech": "adverb"
        },
        "id": {
          "short": "secara kritis",
          "long": "sampai batas tertentu atau derajat yang mungkin merupakan bencana atau bencana",
          "partOfSpeech": "kata keterangan"
        }
      },
      "image": "https://dictionary.hanzi.id/images/372258.jpeg",
      "simplified": "以灾难性的方式",
      "traditional": "以災難性的方式",
      "pinyin": "yǐ zāinàn xìng de fāngshì"
    },
    {
      "id": 372259,
      "translation": {
        "en": {
          "short": "grossly",
          "long": "to an extreme or excessive degree",
          "partOfSpeech": "adverb"
        },
        "id": {
          "short": "terlalu",
          "long": "ke tingkat yang ekstrem atau berlebihan",
          "partOfSpeech": "kata keterangan"
        }
      },
      "image": "https://dictionary.hanzi.id/images/372259.jpeg",
      "simplified": "严重地",
      "traditional": "嚴重地",
      "pinyin": "yánzhòng dì"
    },
    {
      "id": 372260,
      "translation": {
        "en": {
          "short": "unreasonably",
          "long": "to an excessive or unjustifiable degree",
          "partOfSpeech": "adverb"
        },
        "id": {
          "short": "tidak masuk akal",
          "long": "ke tingkat yang berlebihan atau tidak dapat dibenarkan",
          "partOfSpeech": "kata keterangan"
        }
      },
      "image": "https://dictionary.hanzi.id/images/372260.jpeg",
      "simplified": "无理地",
      "traditional": "無理地",
      "pinyin": "wúlǐ de"
    },
    {
      "id": 372261,
      "translation": {
        "en": {
          "short": "wildly",
          "long": "to an excessive or uncontrolled extent",
          "partOfSpeech": "adverb"
        },
        "id": {
          "short": "liar",
          "long": "sampai batas yang berlebihan atau tidak terkendali",
          "partOfSpeech": "kata keterangan"
        }
      },
      "image": "https://dictionary.hanzi.id/images/372261.jpeg",
      "simplified": "疯狂地",
      "traditional": "瘋狂地",
      "pinyin": "fēngkuáng de"
    },
    {
      "id": 372262,
      "translation": {
        "en": {
          "short": "unimaginably",
          "long": "to a degree or extent that is difficult or impossible to imagine",
          "partOfSpeech": "adverb"
        },
        "id": {
          "short": "tak terbayangkan",
          "long": "sampai tingkat tertentu atau tingkat yang sulit atau tidak mungkin dibayangkan",
          "partOfSpeech": "kata keterangan"
        }
      },
      "image": "https://dictionary.hanzi.id/images/372262.jpeg",
      "simplified": "难以想象",
      "traditional": "難以想像",
      "pinyin": "nányǐ xiǎngxiàng"
    },
    {
      "id": 372263,
      "translation": {
        "en": {
          "short": "acutely",
          "long": "in a way that is too extreme or intense",
          "partOfSpeech": "adverb"
        },
        "id": {
          "short": "akut",
          "long": "dengan cara yang terlalu ekstrem atau intens",
          "partOfSpeech": "kata keterangan"
        }
      },
      "image": null,
      "simplified": "敏锐地",
      "traditional": "敏銳地",
      "pinyin": "mǐnruì de"
    },
    {
      "id": 372264,
      "translation": {
        "en": {
          "short": "gravely",
          "long": "in a way that is significantly severe or concerning",
          "partOfSpeech": "adverb"
        },
        "id": {
          "short": "sangat buruk",
          "long": "dengan cara yang secara signifikan parah atau memprihatinkan",
          "partOfSpeech": "kata keterangan"
        }
      },
      "image": "https://dictionary.hanzi.id/images/372264.jpeg",
      "simplified": "严肃地",
      "traditional": "嚴肅地",
      "pinyin": "yánsù de"
    },
    {
      "id": 372266,
      "translation": {
        "en": {
          "short": "terrifically",
          "long": "in an exceptionally excellent manner",
          "partOfSpeech": "adverb"
        },
        "id": {
          "short": "sangat hebat",
          "long": "dengan sangat baik",
          "partOfSpeech": "kata keterangan"
        }
      },
      "image": null,
      "simplified": "异常",
      "traditional": "異常",
      "pinyin": "yìcháng"
    },
    {
      "id": 372268,
      "translation": {
        "en": {
          "short": "unduly",
          "long": "to a greater extent than is reasonable or necessary",
          "partOfSpeech": "adverb"
        },
        "id": {
          "short": "terlalu",
          "long": "ke tingkat yang lebih besar dari yang masuk akal atau perlu",
          "partOfSpeech": "kata keterangan"
        }
      },
      "image": "https://dictionary.hanzi.id/images/372268.jpeg",
      "simplified": "过度",
      "traditional": "過度",
      "pinyin": "guòdù"
    },
    {
      "id": 372271,
      "translation": {
        "en": {
          "short": "awfully",
          "long": "to a very great or extreme extent or degree",
          "partOfSpeech": "adverb"
        },
        "id": {
          "short": "sangat",
          "long": "sampai tingkat atau tingkat yang sangat hebat atau ekstrem",
          "partOfSpeech": "kata keterangan"
        }
      },
      "image": "https://dictionary.hanzi.id/images/372271.jpeg",
      "simplified": "非常",
      "traditional": "非常",
      "pinyin": "fēicháng"
    },
    {
      "id": 372273,
      "translation": {
        "en": {
          "short": "sorely",
          "long": "to a considerable extent",
          "partOfSpeech": "adverb"
        },
        "id": {
          "short": "sangat",
          "long": "sampai batas tertentu",
          "partOfSpeech": "kata keterangan"
        }
      },
      "image": null,
      "simplified": "非常",
      "traditional": "非常",
      "pinyin": "fēicháng"
    },
    {
      "id": 372274,
      "translation": {
        "en": {
          "short": "worst",
          "long": "to the most extreme level, degree, etc.",
          "partOfSpeech": "adverb"
        },
        "id": {
          "short": "terburuk",
          "long": "ke tingkat yang paling ekstrem, derajat, dll.",
          "partOfSpeech": "kata keterangan"
        }
      },
      "image": "https://dictionary.hanzi.id/images/372274.jpeg",
      "simplified": "最糟糕的",
      "traditional": "最糟糕的",
      "pinyin": "zuì zāogāo de"
    },
    {
      "id": 372275,
      "translation": {
        "en": {
          "short": "desperately",
          "long": "to an extreme degree",
          "partOfSpeech": "adverb"
        },
        "id": {
          "short": "mati-matian",
          "long": "sampai tingkat yang ekstrem",
          "partOfSpeech": "kata keterangan"
        }
      },
      "image": "https://dictionary.hanzi.id/images/372275.jpeg",
      "simplified": "强烈地",
      "traditional": "強烈地",
      "pinyin": "qiángliè de"
    },
    {
      "id": 373895,
      "translation": {
        "en": {
          "short": "dreadfully",
          "long": "to an extremely high degree or intensity",
          "partOfSpeech": "adverb"
        },
        "id": {
          "short": "sangat",
          "long": "ke tingkat atau intensitas yang sangat tinggi",
          "partOfSpeech": "kata keterangan"
        }
      },
      "image": "https://dictionary.hanzi.id/images/373895.jpeg",
      "simplified": "可怕地",
      "traditional": "可怕地",
      "pinyin": "kěpà de"
    },
    {
      "id": 382981,
      "translation": {
        "en": {
          "short": "grievously",
          "long": "in a manner that causes great suffering, distress, or harm",
          "partOfSpeech": "adverb"
        },
        "id": {
          "short": "dengan sedih",
          "long": "dengan cara yang menyebabkan penderitaan besar, kesusahan, atau bahaya",
          "partOfSpeech": "kata keterangan"
        }
      },
      "image": "https://dictionary.hanzi.id/images/382981.jpeg",
      "simplified": "严重地",
      "traditional": "嚴重地",
      "pinyin": "yánzhòng dì"
    },
    {
      "id": 386623,
      "translation": {
        "en": {
          "short": "all too",
          "long": "to a degree or extent that is too excessive or more than desired",
          "partOfSpeech": "adverb"
        },
        "id": {
          "short": "semua juga",
          "long": "Pada tingkat atau tingkat yang terlalu berlebihan atau lebih dari yang diinginkan",
          "partOfSpeech": "kata keterangan"
        }
      },
      "image": null,
      "simplified": "也都是",
      "traditional": "也都是",
      "pinyin": "yě dū shì"
    }
  ]
}