{
  "id": 551,
  "title": {
    "en": "Animal Homes",
    "id": "Rumah hewan"
  },
  "description": {
    "en": "Here you will learn the names of animal homes in English such as \"barn\", \"den\", and \"burrow\".",
    "id": "Di sini Anda akan mempelajari nama -nama rumah hewan dalam bahasa Inggris seperti \"gudang\", \"den\", dan \"liang\"."
  },
  "cards": [
    {
      "id": 267568,
      "translation": {
        "en": {
          "short": "hive",
          "long": "a structure in which bees live and make honey",
          "partOfSpeech": "noun"
        },
        "id": {
          "short": "sarang lebah",
          "long": "Struktur di mana lebah hidup dan membuat madu",
          "partOfSpeech": "kata benda"
        }
      },
      "image": "https://dictionary.hanzi.id/images/267568.jpeg",
      "simplified": "蜂巢",
      "traditional": "蜂巢",
      "pinyin": "fēngcháo"
    },
    {
      "id": 267569,
      "translation": {
        "en": {
          "short": "barn",
          "long": "a building on a farm in which people keep their animals, straw, hay, or grains",
          "partOfSpeech": "noun"
        },
        "id": {
          "short": "lumbung",
          "long": "Sebuah bangunan di sebuah peternakan di mana orang memelihara hewan, jerami, jerami, atau biji -bijian mereka",
          "partOfSpeech": "kata benda"
        }
      },
      "image": "https://dictionary.hanzi.id/images/267569.jpeg",
      "simplified": "谷仓",
      "traditional": "穀倉",
      "pinyin": "gǔcāng"
    },
    {
      "id": 267570,
      "translation": {
        "en": {
          "short": "byre",
          "long": "a cowshed or barn used for housing cows or cattle",
          "partOfSpeech": "noun"
        },
        "id": {
          "short": "kandang sapi",
          "long": "Sapi atau gudang yang digunakan untuk sapi perumahan atau sapi",
          "partOfSpeech": "kata benda"
        }
      },
      "image": null,
      "simplified": "拜勒",
      "traditional": "拜勒",
      "pinyin": "bài lè"
    },
    {
      "id": 267571,
      "translation": {
        "en": {
          "short": "pasture",
          "long": "a field covered with grass or similar herbs suitable for animals to graze on",
          "partOfSpeech": "noun"
        },
        "id": {
          "short": "padang rumput",
          "long": "ladang yang ditutupi dengan rumput atau bumbu serupa yang cocok untuk hewan untuk digembalakan",
          "partOfSpeech": "kata benda"
        }
      },
      "image": "https://dictionary.hanzi.id/images/267571.jpeg",
      "simplified": "牧场",
      "traditional": "牧場",
      "pinyin": "mùchǎng"
    },
    {
      "id": 267572,
      "translation": {
        "en": {
          "short": "stable",
          "long": "a building, typically found on a farm, designed to house horses",
          "partOfSpeech": "noun"
        },
        "id": {
          "short": "stabil",
          "long": "Sebuah bangunan, biasanya ditemukan di sebuah peternakan, dirancang untuk menampung kuda",
          "partOfSpeech": "kata benda"
        }
      },
      "image": "https://dictionary.hanzi.id/images/267572.jpeg",
      "simplified": "马厩",
      "traditional": "馬厩",
      "pinyin": "mǎjiù"
    },
    {
      "id": 267573,
      "translation": {
        "en": {
          "short": "tunnel",
          "long": "a burrow or underground den used as a home by certain animals, such as rabbits or foxes",
          "partOfSpeech": "noun"
        },
        "id": {
          "short": "terowongan",
          "long": "Burrow atau ruang bawah tanah yang digunakan sebagai rumah oleh hewan tertentu, seperti kelinci atau rubah",
          "partOfSpeech": "kata benda"
        }
      },
      "image": "https://dictionary.hanzi.id/images/267573.jpeg",
      "simplified": "隧道",
      "traditional": "隧道",
      "pinyin": "suìdào"
    },
    {
      "id": 267574,
      "translation": {
        "en": {
          "short": "hutch",
          "long": "a wooden box with a wired front used for keeping small domesticated animals, such as rabbits, ferrets, etc.",
          "partOfSpeech": "noun"
        },
        "id": {
          "short": "kandang kelinci",
          "long": "Kotak kayu dengan bagian depan kabel yang digunakan untuk memelihara hewan peliharaan kecil, seperti kelinci, musang, dll.",
          "partOfSpeech": "kata benda"
        }
      },
      "image": "https://dictionary.hanzi.id/images/267574.jpeg",
      "simplified": "笼",
      "traditional": "籠",
      "pinyin": "lóng"
    },
    {
      "id": 267575,
      "translation": {
        "en": {
          "short": "web",
          "long": "a net of thin threads made by a spider to catch insects for food",
          "partOfSpeech": "noun"
        },
        "id": {
          "short": "web",
          "long": "Jaring benang tipis yang dibuat oleh laba -laba untuk menangkap serangga untuk makanan",
          "partOfSpeech": "kata benda"
        }
      },
      "image": "https://dictionary.hanzi.id/images/267575.jpeg",
      "simplified": "蜘蛛网",
      "traditional": "蜘蛛網",
      "pinyin": "zhīzhū wǎng"
    },
    {
      "id": 267576,
      "translation": {
        "en": {
          "short": "lair",
          "long": "a place where a wild animal lives, hides, or takes refuge",
          "partOfSpeech": "noun"
        },
        "id": {
          "short": "sarang",
          "long": "tempat di mana seekor binatang liar hidup, bersembunyi, atau berlindung",
          "partOfSpeech": "kata benda"
        }
      },
      "image": "https://dictionary.hanzi.id/images/267576.jpeg",
      "simplified": "巢穴",
      "traditional": "巢穴",
      "pinyin": "cháoxué"
    },
    {
      "id": 267577,
      "translation": {
        "en": {
          "short": "nest",
          "long": "a structure that a bird makes for laying eggs or keeping the hatchlings in",
          "partOfSpeech": "noun"
        },
        "id": {
          "short": "sarang",
          "long": "Struktur yang dibuat seekor burung untuk bertelur atau menjaga tukik",
          "partOfSpeech": "kata benda"
        }
      },
      "image": "https://dictionary.hanzi.id/images/267577.jpeg",
      "simplified": "巢",
      "traditional": "巢",
      "pinyin": "Cháo"
    },
    {
      "id": 267578,
      "translation": {
        "en": {
          "short": "honeycomb",
          "long": "a structure that is made by bees, consisting of six-sided cells where they store their honey",
          "partOfSpeech": "noun"
        },
        "id": {
          "short": "sarang madu",
          "long": "Struktur yang dibuat oleh lebah, terdiri dari sel enam sisi tempat mereka menyimpan madu mereka",
          "partOfSpeech": "kata benda"
        }
      },
      "image": "https://dictionary.hanzi.id/images/267578.jpeg",
      "simplified": "蜂窝",
      "traditional": "蜂窩",
      "pinyin": "fēngwō"
    },
    {
      "id": 267579,
      "translation": {
        "en": {
          "short": "cobweb",
          "long": "a tangled net of threads that a spider makes in order to catch insects",
          "partOfSpeech": "noun"
        },
        "id": {
          "short": "Laba -laba",
          "long": "Jaring utas kusut yang dibuat laba -laba untuk menangkap serangga",
          "partOfSpeech": "kata benda"
        }
      },
      "image": "https://dictionary.hanzi.id/images/267579.jpeg",
      "simplified": "蛛网",
      "traditional": "蛛網",
      "pinyin": "zhūwǎng"
    },
    {
      "id": 267580,
      "translation": {
        "en": {
          "short": "anthill",
          "long": "a large mound of earth created by ants as their home and for storing food",
          "partOfSpeech": "noun"
        },
        "id": {
          "short": "sarang semut",
          "long": "gundukan besar bumi yang diciptakan oleh semut sebagai rumah mereka dan untuk menyimpan makanan",
          "partOfSpeech": "kata benda"
        }
      },
      "image": null,
      "simplified": "垤",
      "traditional": "垤",
      "pinyin": "dié"
    },
    {
      "id": 267581,
      "translation": {
        "en": {
          "short": "roost",
          "long": "a place where birds settle and rest",
          "partOfSpeech": "noun"
        },
        "id": {
          "short": "bertengger",
          "long": "Tempat di mana burung tenang dan beristirahat",
          "partOfSpeech": "kata benda"
        }
      },
      "image": "https://dictionary.hanzi.id/images/267581.jpeg",
      "simplified": "鸡窝",
      "traditional": "雞窩",
      "pinyin": "jīwō"
    },
    {
      "id": 267582,
      "translation": {
        "en": {
          "short": "rookery",
          "long": "a collection of nests that a bird colony, such as rooks build for breeding",
          "partOfSpeech": "noun"
        },
        "id": {
          "short": "heboh",
          "long": "Koleksi sarang yang membuat koloni burung, seperti benteng untuk berkembang biak",
          "partOfSpeech": "kata benda"
        }
      },
      "image": null,
      "simplified": "群居地",
      "traditional": "群居地",
      "pinyin": "qúnjū de"
    },
    {
      "id": 267583,
      "translation": {
        "en": {
          "short": "perch",
          "long": "a place where a bird rests or settles, such as a branch or a rod",
          "partOfSpeech": "noun"
        },
        "id": {
          "short": "hinggap",
          "long": "tempat di mana seekor burung beristirahat atau mengendap, seperti cabang atau batang",
          "partOfSpeech": "kata benda"
        }
      },
      "image": "https://dictionary.hanzi.id/images/267583.jpeg",
      "simplified": "栖",
      "traditional": "棲",
      "pinyin": "qī"
    },
    {
      "id": 267585,
      "translation": {
        "en": {
          "short": "aerie",
          "long": "a lofty nest of a bird of prey, typically built on a cliff or high place",
          "partOfSpeech": "noun"
        },
        "id": {
          "short": "Aerie",
          "long": "Sarang yang tinggi dari burung pemangsa, biasanya dibangun di atas tebing atau tempat tinggi",
          "partOfSpeech": "kata benda"
        }
      },
      "image": null,
      "simplified": "鹰巢",
      "traditional": "鷹巢",
      "pinyin": "yīng Cháo"
    },
    {
      "id": 267586,
      "translation": {
        "en": {
          "short": "warren",
          "long": "a network of interconnected underground tunnels and chambers where rabbits or other small burrowing animals live",
          "partOfSpeech": "noun"
        },
        "id": {
          "short": "Warren",
          "long": "Jaringan terowongan dan ruang bawah tanah yang saling berhubungan di mana kelinci atau hewan kecil lainnya hidup",
          "partOfSpeech": "kata benda"
        }
      },
      "image": null,
      "simplified": "养兔场",
      "traditional": "養兔場",
      "pinyin": "yǎng tù cháng"
    },
    {
      "id": 267587,
      "translation": {
        "en": {
          "short": "territory",
          "long": "an area occupied by an animal or a group of animals that is defended against others",
          "partOfSpeech": "noun"
        },
        "id": {
          "short": "wilayah",
          "long": "Area yang ditempati oleh hewan atau sekelompok hewan yang dipertahankan terhadap orang lain",
          "partOfSpeech": "kata benda"
        }
      },
      "image": null,
      "simplified": "领土",
      "traditional": "領土",
      "pinyin": "lǐngtǔ"
    },
    {
      "id": 267588,
      "translation": {
        "en": {
          "short": "sett",
          "long": "a badger's den or burrow",
          "partOfSpeech": "noun"
        },
        "id": {
          "short": "set",
          "long": "Badger's Den atau Burrow",
          "partOfSpeech": "kata benda"
        }
      },
      "image": null,
      "simplified": "塞特",
      "traditional": "塞特",
      "pinyin": "Sāi tè"
    },
    {
      "id": 267589,
      "translation": {
        "en": {
          "short": "rabbit hole",
          "long": "a small hole or tunnel in the ground that is dug by rabbits and used as a burrow or shelter",
          "partOfSpeech": "noun"
        },
        "id": {
          "short": "lubang kelinci",
          "long": "Lubang kecil atau terowongan di tanah yang digali oleh kelinci dan digunakan sebagai liang atau tempat berlindung",
          "partOfSpeech": "kata benda"
        }
      },
      "image": null,
      "simplified": "兔子洞",
      "traditional": "兔子洞",
      "pinyin": "tùzi dòng"
    },
    {
      "id": 267590,
      "translation": {
        "en": {
          "short": "molehill",
          "long": "a small hill or mound of earth created by moles as they burrow underground",
          "partOfSpeech": "noun"
        },
        "id": {
          "short": "Molehill",
          "long": "bukit kecil atau gundukan bumi yang diciptakan oleh tahi lalat saat mereka menggali di bawah tanah",
          "partOfSpeech": "kata benda"
        }
      },
      "image": null,
      "simplified": "莫尔希尔",
      "traditional": "莫爾希爾",
      "pinyin": "Mò ěr Xīěr"
    },
    {
      "id": 267591,
      "translation": {
        "en": {
          "short": "lodge",
          "long": "the nest of an otter or a beaver",
          "partOfSpeech": "noun"
        },
        "id": {
          "short": "mengajukan",
          "long": "sarang berang atau berang -berang",
          "partOfSpeech": "kata benda"
        }
      },
      "image": null,
      "simplified": "小屋",
      "traditional": "小屋",
      "pinyin": "xiǎowū"
    },
    {
      "id": 267592,
      "translation": {
        "en": {
          "short": "habitat",
          "long": "the place or area in which certain animals, birds, or plants naturally exist, lives, and grows",
          "partOfSpeech": "noun"
        },
        "id": {
          "short": "habitat",
          "long": "Tempat atau area di mana hewan, burung, atau tumbuhan tertentu secara alami ada, hidup, dan tumbuh",
          "partOfSpeech": "kata benda"
        }
      },
      "image": "https://dictionary.hanzi.id/images/267592.jpeg",
      "simplified": "栖息地",
      "traditional": "棲息地",
      "pinyin": "qīxī dì"
    },
    {
      "id": 267593,
      "translation": {
        "en": {
          "short": "den",
          "long": "the hidden place where a wild predatory animal lives",
          "partOfSpeech": "noun"
        },
        "id": {
          "short": "sarang",
          "long": "tempat tersembunyi di mana hewan predator liar hidup",
          "partOfSpeech": "kata benda"
        }
      },
      "image": "https://dictionary.hanzi.id/images/267593.jpeg",
      "simplified": "巢穴",
      "traditional": "巢穴",
      "pinyin": "cháoxué"
    },
    {
      "id": 267594,
      "translation": {
        "en": {
          "short": "burrow",
          "long": "a hole that an animal digs in the ground to use as a shelter",
          "partOfSpeech": "noun"
        },
        "id": {
          "short": "liang",
          "long": "lubang yang digali hewan di tanah untuk digunakan sebagai tempat penampungan",
          "partOfSpeech": "kata benda"
        }
      },
      "image": "https://dictionary.hanzi.id/images/267594.jpeg",
      "simplified": "地下洞穴",
      "traditional": "地下洞穴",
      "pinyin": "dìxià dòngxué"
    },
    {
      "id": 267597,
      "translation": {
        "en": {
          "short": "fold",
          "long": "a group of sheep kept together for breeding purposes",
          "partOfSpeech": "noun"
        },
        "id": {
          "short": "melipat",
          "long": "sekelompok domba disimpan bersama untuk tujuan pemuliaan",
          "partOfSpeech": "kata benda"
        }
      },
      "image": null,
      "simplified": "合拢",
      "traditional": "合攏",
      "pinyin": "hélǒng"
    },
    {
      "id": 267598,
      "translation": {
        "en": {
          "short": "pen",
          "long": "a designated enclosed area where domesticated animals such as pigs, goats, and chickens are housed",
          "partOfSpeech": "noun"
        },
        "id": {
          "short": "pena",
          "long": "Area tertutup yang ditunjuk di mana hewan peliharaan seperti babi, kambing, dan ayam ditempatkan",
          "partOfSpeech": "kata benda"
        }
      },
      "image": null,
      "simplified": "笔",
      "traditional": "筆",
      "pinyin": "bǐ"
    },
    {
      "id": 267601,
      "translation": {
        "en": {
          "short": "aquarium",
          "long": "a large container usually made of glass that is filled with water in which fish and other sea creatures are kept",
          "partOfSpeech": "noun"
        },
        "id": {
          "short": "akuarium",
          "long": "wadah besar yang biasanya terbuat dari kaca yang diisi dengan air di mana ikan dan makhluk laut lainnya disimpan",
          "partOfSpeech": "kata benda"
        }
      },
      "image": "https://dictionary.hanzi.id/images/267601.jpeg",
      "simplified": "水族馆",
      "traditional": "水族館",
      "pinyin": "shuǐzú guǎn"
    },
    {
      "id": 267602,
      "translation": {
        "en": {
          "short": "cote",
          "long": "a small shelter or coop, usually for poultry or pigeons",
          "partOfSpeech": "noun"
        },
        "id": {
          "short": "kandang",
          "long": "tempat penampungan atau kandang kecil, biasanya untuk unggas atau merpati",
          "partOfSpeech": "kata benda"
        }
      },
      "image": "https://dictionary.hanzi.id/images/267602.jpeg",
      "simplified": "栏",
      "traditional": "欄",
      "pinyin": "lán"
    },
    {
      "id": 267603,
      "translation": {
        "en": {
          "short": "sty",
          "long": "a small, enclosed area where pigs are kept",
          "partOfSpeech": "noun"
        },
        "id": {
          "short": "tembel",
          "long": "Area kecil yang tertutup tempat babi disimpan",
          "partOfSpeech": "kata benda"
        }
      },
      "image": null,
      "simplified": "圈",
      "traditional": "圈",
      "pinyin": "juān"
    },
    {
      "id": 267604,
      "translation": {
        "en": {
          "short": "cage",
          "long": "a framework made of metal bars or wires in which animals or birds can be kept",
          "partOfSpeech": "noun"
        },
        "id": {
          "short": "kurungan",
          "long": "kerangka kerja yang terbuat dari batang logam atau kabel di mana hewan atau burung dapat disimpan",
          "partOfSpeech": "kata benda"
        }
      },
      "image": "https://dictionary.hanzi.id/images/267604.jpeg",
      "simplified": "笼",
      "traditional": "籠",
      "pinyin": "lóng"
    },
    {
      "id": 267605,
      "translation": {
        "en": {
          "short": "kennel",
          "long": "a small structure used as a shelter for a dog",
          "partOfSpeech": "noun"
        },
        "id": {
          "short": "Kennel",
          "long": "Struktur kecil yang digunakan sebagai tempat berlindung untuk seekor anjing",
          "partOfSpeech": "kata benda"
        }
      },
      "image": "https://dictionary.hanzi.id/images/267605.jpeg",
      "simplified": "狗窝",
      "traditional": "狗窩",
      "pinyin": "gǒuwō"
    },
    {
      "id": 267606,
      "translation": {
        "en": {
          "short": "oceanarium",
          "long": "a large marine aquarium in which fish and other sea creatures are displayed to the public or studied by scientists",
          "partOfSpeech": "noun"
        },
        "id": {
          "short": "Oceanarium",
          "long": "Akuarium laut besar di mana ikan dan makhluk laut lainnya ditampilkan kepada publik atau dipelajari oleh para ilmuwan",
          "partOfSpeech": "kata benda"
        }
      },
      "image": "https://dictionary.hanzi.id/images/267606.jpeg",
      "simplified": "海洋馆",
      "traditional": "海洋館",
      "pinyin": "hǎiyáng guǎn"
    },
    {
      "id": 267607,
      "translation": {
        "en": {
          "short": "dolphinarium",
          "long": "an aquarium for dolphins",
          "partOfSpeech": "noun"
        },
        "id": {
          "short": "Dolphinarium",
          "long": "Akuarium untuk Lumba -lumba",
          "partOfSpeech": "kata benda"
        }
      },
      "image": "https://dictionary.hanzi.id/images/267607.jpeg",
      "simplified": "海豚馆",
      "traditional": "海豚館",
      "pinyin": "hǎitún guǎn"
    },
    {
      "id": 267609,
      "translation": {
        "en": {
          "short": "aviary",
          "long": "a large cage or building where birds are kept",
          "partOfSpeech": "noun"
        },
        "id": {
          "short": "kandang burung",
          "long": "kandang besar atau bangunan tempat burung disimpan",
          "partOfSpeech": "kata benda"
        }
      },
      "image": "https://dictionary.hanzi.id/images/267609.jpeg",
      "simplified": "鸟舍",
      "traditional": "鳥舍",
      "pinyin": "diǎo shě"
    },
    {
      "id": 267610,
      "translation": {
        "en": {
          "short": "fishbowl",
          "long": "a glass container that fish are kept in it as pets",
          "partOfSpeech": "noun"
        },
        "id": {
          "short": "mangkuk ikan",
          "long": "wadah kaca yang disimpan ikan di dalamnya sebagai hewan peliharaan",
          "partOfSpeech": "kata benda"
        }
      },
      "image": "https://dictionary.hanzi.id/images/267610.jpeg",
      "simplified": "鱼缸",
      "traditional": "魚缸",
      "pinyin": "yúgāng"
    },
    {
      "id": 267611,
      "translation": {
        "en": {
          "short": "beehive",
          "long": "a natural or human-made structure where bees live",
          "partOfSpeech": "noun"
        },
        "id": {
          "short": "sarang lebah",
          "long": "struktur alami atau buatan manusia di mana lebah tinggal",
          "partOfSpeech": "kata benda"
        }
      },
      "image": "https://dictionary.hanzi.id/images/267611.jpeg",
      "simplified": "蜂窝",
      "traditional": "蜂窩",
      "pinyin": "fēngwō"
    },
    {
      "id": 327318,
      "translation": {
        "en": {
          "short": "animal shelter",
          "long": "a temporary housing and care facility for lost, abandoned, or surrendered domesticated animals, with the aim of finding them permanent homes",
          "partOfSpeech": "noun"
        },
        "id": {
          "short": "penampungan hewan",
          "long": "fasilitas perumahan dan perawatan sementara untuk hewan peliharaan yang hilang, ditinggalkan, atau menyerah, dengan tujuan menemukan mereka rumah permanen",
          "partOfSpeech": "kata benda"
        }
      },
      "image": null,
      "simplified": "动物收容所",
      "traditional": "動物收容所",
      "pinyin": "dòngwù shōuróng suǒ"
    },
    {
      "id": 327319,
      "translation": {
        "en": {
          "short": "pound",
          "long": "a small, usually enclosed, area where domesticated animals such as dogs, pigs, or cattle are kept",
          "partOfSpeech": "noun"
        },
        "id": {
          "short": "pound",
          "long": "Area kecil, biasanya tertutup, di mana hewan peliharaan seperti anjing, babi, atau ternak disimpan",
          "partOfSpeech": "kata benda"
        }
      },
      "image": null,
      "simplified": "磅",
      "traditional": "磅",
      "pinyin": "bàng"
    },
    {
      "id": 328762,
      "translation": {
        "en": {
          "short": "apiary",
          "long": "a place where bees are kept and honey is produced",
          "partOfSpeech": "noun"
        },
        "id": {
          "short": "tempat pemeliharaan lebah",
          "long": "tempat di mana lebah disimpan dan madu diproduksi",
          "partOfSpeech": "kata benda"
        }
      },
      "image": null,
      "simplified": "蜂房",
      "traditional": "蜂房",
      "pinyin": "fēngfáng"
    },
    {
      "id": 328763,
      "translation": {
        "en": {
          "short": "shed",
          "long": "a simple and small cottage-like building that is built to store things or shelter animals",
          "partOfSpeech": "noun"
        },
        "id": {
          "short": "gudang",
          "long": "Bangunan seperti pondok sederhana dan kecil yang dibangun untuk menyimpan barang-barang atau hewan perlindungan",
          "partOfSpeech": "kata benda"
        }
      },
      "image": null,
      "simplified": "棚",
      "traditional": "棚",
      "pinyin": "péng"
    },
    {
      "id": 271046,
      "translation": {
        "en": {
          "short": "form",
          "long": "a shallow hole or nest made by a hare for shelter or protection",
          "partOfSpeech": "noun"
        },
        "id": {
          "short": "membentuk",
          "long": "lubang atau sarang dangkal yang dibuat oleh kelinci untuk perlindungan atau perlindungan",
          "partOfSpeech": "kata benda"
        }
      },
      "image": null,
      "simplified": "形式",
      "traditional": "形式",
      "pinyin": "xíngshì"
    },
    {
      "id": 291003,
      "translation": {
        "en": {
          "short": "columbary",
          "long": "a structure or aviary for housing domesticated pigeons or doves",
          "partOfSpeech": "noun"
        },
        "id": {
          "short": "columbary",
          "long": "Struktur atau kandang burung untuk merpati atau merpati jinak",
          "partOfSpeech": "kata benda"
        }
      },
      "image": null,
      "simplified": "鸽房",
      "traditional": "鴿房",
      "pinyin": "gēfáng"
    },
    {
      "id": 328765,
      "translation": {
        "en": {
          "short": "coop",
          "long": "a small building to confine poultry, usually in a farm",
          "partOfSpeech": "noun"
        },
        "id": {
          "short": "mengurung",
          "long": "Sebuah bangunan kecil untuk membatasi unggas, biasanya di pertanian",
          "partOfSpeech": "kata benda"
        }
      },
      "image": "https://dictionary.hanzi.id/images/328765.jpeg",
      "simplified": "笼",
      "traditional": "籠",
      "pinyin": "lóng"
    },
    {
      "id": 328771,
      "translation": {
        "en": {
          "short": "drey",
          "long": "a squirrel's nest in a tree",
          "partOfSpeech": "noun"
        },
        "id": {
          "short": "sarang tupai",
          "long": "sarang tupai di pohon",
          "partOfSpeech": "kata benda"
        }
      },
      "image": "https://dictionary.hanzi.id/images/328771.jpeg",
      "simplified": "德雷",
      "traditional": "德雷",
      "pinyin": "Dé Léi"
    },
    {
      "id": 328774,
      "translation": {
        "en": {
          "short": "menagerie",
          "long": "a collection of live animals kept for exhibition, usually in a zoo or as part of a traveling circus",
          "partOfSpeech": "noun"
        },
        "id": {
          "short": "Menagerie",
          "long": "Koleksi hewan hidup disimpan untuk pameran, biasanya di kebun binatang atau sebagai bagian dari sirkus perjalanan",
          "partOfSpeech": "kata benda"
        }
      },
      "image": "https://dictionary.hanzi.id/images/328774.jpeg",
      "simplified": "动物园",
      "traditional": "動物園",
      "pinyin": "dòngwù yuán"
    },
    {
      "id": 328775,
      "translation": {
        "en": {
          "short": "zoo",
          "long": "a place where many kinds of animals are kept for exhibition, breeding, and protection",
          "partOfSpeech": "noun"
        },
        "id": {
          "short": "kebun binatang",
          "long": "tempat di mana banyak jenis hewan disimpan untuk pameran, pembiakan, dan perlindungan",
          "partOfSpeech": "kata benda"
        }
      },
      "image": "https://dictionary.hanzi.id/images/328775.jpeg",
      "simplified": "动物园",
      "traditional": "動物園",
      "pinyin": "dòngwù yuán"
    },
    {
      "id": 330964,
      "translation": {
        "en": {
          "short": "formicary",
          "long": "a nest or dwelling place of ants",
          "partOfSpeech": "noun"
        },
        "id": {
          "short": "format",
          "long": "sarang atau tempat tinggal semut",
          "partOfSpeech": "kata benda"
        }
      },
      "image": null,
      "simplified": "蚁巢",
      "traditional": "蟻巢",
      "pinyin": "yǐ Cháo"
    },
    {
      "id": 330971,
      "translation": {
        "en": {
          "short": "redd",
          "long": "a spawning nest created by salmonids, such as salmon or trout, in gravel-bottomed streams or rivers",
          "partOfSpeech": "noun"
        },
        "id": {
          "short": "Redd",
          "long": "Sarang pemijahan yang dibuat oleh salmonid, seperti salmon atau trout, dalam aliran atau sungai kerikil",
          "partOfSpeech": "kata benda"
        }
      },
      "image": null,
      "simplified": "雷德",
      "traditional": "雷德",
      "pinyin": "Léidé"
    },
    {
      "id": 330976,
      "translation": {
        "en": {
          "short": "earth",
          "long": "a tunnel or hole dug underground by some animals, such as badgers, foxes, rabbits, or moles, for shelter and protection",
          "partOfSpeech": "noun"
        },
        "id": {
          "short": "bumi",
          "long": "Sebuah terowongan atau lubang yang digali di bawah tanah oleh beberapa hewan, seperti musang, rubah, kelinci, atau tahi lalat, untuk perlindungan dan perlindungan",
          "partOfSpeech": "kata benda"
        }
      },
      "image": null,
      "simplified": "地",
      "traditional": "地",
      "pinyin": "de"
    },
    {
      "id": 330981,
      "translation": {
        "en": {
          "short": "holt",
          "long": "a den or shelter made by otters near a river or water source for protection, resting, grooming, and raising young",
          "partOfSpeech": "noun"
        },
        "id": {
          "short": "suaka",
          "long": "Sarang atau tempat berlindung yang dibuat oleh berang -berang di dekat sungai atau sumber air untuk perlindungan, istirahat, perawatan, dan membesarkan anak muda",
          "partOfSpeech": "kata benda"
        }
      },
      "image": null,
      "simplified": "林地",
      "traditional": "林地",
      "pinyin": "líndì"
    }
  ]
}